oee_lib/__init__.py
oee_lib/calculator.py
performance_calculator-1.0.1.dist-info/METADATA
performance_calculator-1.0.1.dist-info/WHEEL
performance_calculator-1.0.1.dist-info/licenses/LICENSE
performance_calculator-1.0.1.dist-info/RECORD
