Metadata-Version: 2.4
Name: performance_calculator
Version: 1.0.1
Summary: A simple Python OEE Calculator
Project-URL: Homepage, https://github.com/sergio-oliveira-br/oee-calc-lib
Project-URL: Bug Tracker, https://github.com/sergio-oliveira-br/oee-calc-lib/issues
Author-email: Sergio Oliveira <oliveira-sergio@outlook.com>
License-Expression: MIT
License-File: LICENSE
Classifier: License :: OSI Approved :: MIT License
Classifier: Operating System :: OS Independent
Classifier: Programming Language :: Python :: 3
Requires-Python: >=3.7
